Workbook
Name _ftn1: 'Normativa Especies'!$C$997
Name _ftn10: 'Normativa Especies'!$C$1020
Name _ftn11: 'Normativa Especies'!$C$1027
Name _ftn12: 'Normativa Especies'!$C$1024
Name _ftn7: 'Normativa Especies'!$C$1006
Name _ftn9: 'Normativa Especies'!$C$1017
Name _ftnref10: 'Normativa Especies'!$C$794
Name _ftnref11: 'Normativa Especies'!$C$919
Name _ftnref12: 'Normativa Especies'!$C$885
Name _ftnref7: 'Normativa Especies'!$C$598
Name _ftnref8: 'Normativa Especies'!$C$417
Name _ftnref9: 'Normativa Especies'!$C$695

Sheet 30TVK15
A1: Grupo | B1: Nombre | C1: Genero | D1: Especie | E1: Infra | F1: CUTM10x10 | G1: EstadoCUTM | H1: FechaCUTM | I1: OrigenCUTM | J1: DescripcionOrigenCUTM | K1: Autor | L1: Reino | M1: Division | N1: Clase | O1: Orden | P1: Familia
A2: Mamíferos | B2: Rattus norvegicus | C2: Rattus | D2: norvegicus | F2: 30TVK15 | G2: Confirmada | H2: 39083 | I2: Atlas y/o Libro Rojo | J2: Atlas y Libro Rojo de los Mamíferos Terrestres de España | K2: (Berkenhout, 1769) | L2: Animalia | M2: Chordata | N2: Mammalia | O2: Roedores | P2: Muridae
A3: Aves | B3: Remiz pendulinus | C3: Remiz | D3: pendulinus | F3: 30TVK15 | G3: Confirmada | H3: 37987 | I3: Atlas y/o Libro Rojo | J3: Libro Rojo de las Aves de España | K3: Linnaeus,1758 | L3: Animalia | M3: Chordata | N3: Aves | O3: Paseriformes | P3: Remizidae
A4: Mamíferos | B4: Apodemus sylvaticus | C4: Apodemus | D4: sylvaticus | F4: 30TVK15 | G4: Confirmada | H4: 39083 | I4: Atlas y/o Libro Rojo | J4: Atlas y Libro Rojo de los Mamíferos Terrestres de España | K4: (Linnaeus, 1758) | L4: Animalia | M4: Chordata | N4: Mammalia | O4: Roedores | P4: Muridae
A5: Peces continentales | B5: Barbus bocagei | C5: Barbus | D5: bocagei | F5: 30TVK15 | G5: Confirmada | H5: 36892 | I5: Atlas y/o Libro Rojo | J5: Atlas y Libro Rojo de los Peces Continentales de España | K5: Steindachner, 1864 | L5: Animalia | M5: Chordata | N5: Actinopterygii | O5: Cypriniformes | P5: Cyprinidae
A6: Mamíferos | B6: Vulpes vulpes | C6: Vulpes | D6: vulpes | F6: 30TVK15 | G6: Confirmada | H6: 39083 | I6: Atlas y/o Libro Rojo | J6: Atlas y Libro Rojo de los Mamíferos Terrestres de España | K6: (Linnaeus, 1758) | L6: Animalia | M6: Chordata | N6: Mammalia | O6: Carnívoros | P6: Canidae
A7: Peces continentales | B7: Cobitis paludica | C7: Cobitis | D7: paludica | F7: 30TVK15 | G7: No Confirmada | H7: 39814 | I7: Seguimiento | J7: Ictiofauna Continental Española, 2011 | K7: De Buen, 1930 | L7: Animalia | M7: Chordata | N7: Actinopterygii | O7: Cypriniformes | P7: Cobitidae
A8: Peces continentales | B8: Cobitis paludica | C8: Cobitis | D8: paludica | F8: 30TVK15 | G8: Confirmada | H8: 36892 | I8: Atlas y/o Libro Rojo | J8: Atlas y Libro Rojo de los Peces Continentales de España | K8: De Buen, 1930 | L8: Animalia | M8: Chordata | N8: Actinopterygii | O8: Cypriniformes | P8: Cobitidae
A9: Mamíferos | B9: Crocidura russula | C9: Crocidura | D9: russula | F9: 30TVK15 | G9: Confirmada | H9: 39083 | I9: Atlas y/o Libro Rojo | J9: Atlas y Libro Rojo de los Mamíferos Terrestres de España | K9: (Hermann, 1780) | L9: Animalia | M9: Chordata | N9: Mammalia | O9: Soricomorfos | P9: Soricidae
A10: Reptiles | B10: Psammodromus algirus | C10: Psammodromus | D10: algirus | F10: 30TVK15 | G10: Confirmada | H10: 37257 | I10: Otros | J10: Base de Datos Herpetológica, 2011 | K10: (Linnaeus, 1758) | L10: Animalia | M10: Chordata | N10: Reptilia | O10: Squamata | P10: Lacertidae
A11: Mamíferos | B11: Mus musculus | C11: Mus | D11: musculus | F11: 30TVK15 | G11: Confirmada | H11: 39083 | I11: Atlas y/o Libro Rojo | J11: Atlas y Libro Rojo de los Mamíferos Terrestres de España | K11: - | L11: Animalia | M11: Chordata | N11: Mammalia | O11: Roedores | P11: Muridae
A12: Aves | B12: Cecropis daurica | C12: Cecropis | D12: daurica | F12: 30TVK15 | G12: Confirmada | H12: 37987 | I12: Atlas y/o Libro Rojo | J12: Libro Rojo de las Aves de España | K12: Linneo,1771 | L12: Animalia | M12: Chordata | N12: Aves | O12: Paseriformes | P12: Hirundinidae
A13: Aves | B13: Circus aeruginosus | C13: Circus | D13: aeruginosus | F13: 30TVK15 | G13: Confirmada | H13: 38718 | I13: Otros | J13: Seguimientos Específicos | K13: Linnaeus,1758 | L13: Animalia | M13: Chordata | N13: Aves | O13: Falconiformes | P13: Accipitridae
... A135: Aves | B135: Oenanthe hispanica | C135: Oenanthe | D135: hispanica | F135: 30TVK15 | G135: Confirmada | H135: 37987 | I135: Atlas y/o Libro Rojo | J135: Libro Rojo de las Aves de España | K135: Linnaeus,1758 | L135: Animalia | M135: Chordata | N135: Aves | O135: Paseriformes | P135: Turdidae

Sheet 🦅 Inventario Fauna
A1: Inventario Faunístico — Proyecto
A2: CATEGORÍAS: | B2: 🟠 En peligro de extinción | C2: 🟡 Vulnerable | D2: 🟢 Otro
A3: Nombre científico | B3: Nombre común | C3: Grupo | D3: LESRPE/CEEA | E3: Cat. Madrid | F3: Normativa autonómica | H3: Cat. España | I3: Cat. amenaza (Listado/Catálogo Madrid)
A4: Rattus norvegicus | B4: — | C4: Mamíferos | D4: — | E4: — | F4: — | H4: =IFERROR(INDEX('Normativa Especies'!$H$2:$H$995,MATCH(TRIM(A4),'Normativa Especies'!$M$2:$M$995,0)),"-") -> - | I4: =IFERROR(INDEX(FAUNA!$D$2:$D$134,MATCH(TRIM(A4),FAUNA!$E$1:E134,0)),"-") -> -
A5: Remiz pendulinus | B5: Pájaro moscón | C5: Aves | D5: LESRPE | E5: — | F5: — | H5: =IFERROR(INDEX('Normativa Especies'!$H$2:$H$995,MATCH(TRIM(A5),'Normativa Especies'!$M$2:$M$995,0)),"-") -> LESRPE | I5: =IFERROR(INDEX(FAUNA!$D$2:$D$134,MATCH(TRIM(A5),FAUNA!$E$1:E135,0)),"-") -> -
A6: Apodemus sylvaticus | B6: — | C6: Mamíferos | D6: — | E6: — | F6: — | H6: =IFERROR(INDEX('Normativa Especies'!$H$2:$H$995,MATCH(TRIM(A6),'Normativa Especies'!$M$2:$M$995,0)),"-") -> - | I6: =IFERROR(INDEX(FAUNA!$D$2:$D$134,MATCH(TRIM(A6),FAUNA!$E$1:E136,0)),"-") -> -
A7: Barbus bocagei | B7: — | C7: Peces continentales | D7: — | E7: — | F7: — | H7: =IFERROR(INDEX('Normativa Especies'!$H$2:$H$995,MATCH(TRIM(A7),'Normativa Especies'!$M$2:$M$995,0)),"-") -> - | I7: =IFERROR(INDEX(FAUNA!$D$2:$D$134,MATCH(TRIM(A7),FAUNA!$E$1:E137,0)),"-") -> -
A8: Vulpes vulpes | B8: — | C8: Mamíferos | D8: — | E8: — | F8: — | H8: =IFERROR(INDEX('Normativa Especies'!$H$2:$H$995,MATCH(TRIM(A8),'Normativa Especies'!$M$2:$M$995,0)),"-") -> - | I8: =IFERROR(INDEX(FAUNA!$D$2:$D$134,MATCH(TRIM(A8),FAUNA!$E$1:E138,0)),"-") -> -
A9: Cobitis paludica | B9: — | C9: Peces continentales | D9: — | E9: — | F9: — | H9: =IFERROR(INDEX('Normativa Especies'!$H$2:$H$995,MATCH(TRIM(A9),'Normativa Especies'!$M$2:$M$995,0)),"-") -> - | I9: =IFERROR(INDEX(FAUNA!$D$2:$D$134,MATCH(TRIM(A9),FAUNA!$E$1:E139,0)),"-") -> -
A10: Crocidura russula | B10: — | C10: Mamíferos | D10: — | E10: — | F10: — | H10: =IFERROR(INDEX('Normativa Especies'!$H$2:$H$995,MATCH(TRIM(A10),'Normativa Especies'!$M$2:$M$995,0)),"-") -> - | I10: =IFERROR(INDEX(FAUNA!$D$2:$D$134,MATCH(TRIM(A10),FAUNA!$E$1:E140,0)),"-") -> -
A11: Psammodromus algirus | B11: Lagartija colilarga | C11: Reptiles | D11: LESRPE | E11: — | F11: — | H11: =IFERROR(INDEX('Normativa Especies'!$H$2:$H$995,MATCH(TRIM(A11),'Normativa Especies'!$M$2:$M$995,0)),"-") -> LESRPE | I11: =IFERROR(INDEX(FAUNA!$D$2:$D$134,MATCH(TRIM(A11),FAUNA!$E$1:E141,0)),"-") -> -
A12: Mus musculus | B12: — | C12: Mamíferos | D12: — | E12: — | F12: — | H12: =IFERROR(INDEX('Normativa Especies'!$H$2:$H$995,MATCH(TRIM(A12),'Normativa Especies'!$M$2:$M$995,0)),"-") -> - | I12: =IFERROR(INDEX(FAUNA!$D$2:$D$134,MATCH(TRIM(A12),FAUNA!$E$1:E142,0)),"-") -> -
A13: Cecropis daurica | B13: Golondrina daúrica | C13: Aves | D13: LESRPE | E13: — | F13: — | H13: =IFERROR(INDEX('Normativa Especies'!$H$2:$H$995,MATCH(TRIM(A13),'Normativa Especies'!$M$2:$M$995,0)),"-") -> - | I13: =IFERROR(INDEX(FAUNA!$D$2:$D$134,MATCH(TRIM(A13),FAUNA!$E$1:E143,0)),"-") -> -
A14: Circus aeruginosus | B14: — | C14: Aves | D14: LESRPE | E14: SENSIBLES | F14: Decreto 18/1992, de 26 de marzo, por el | H14: =IFERROR(INDEX('Normativa Especies'!$H$2:$H$995,MATCH(TRIM(A14),'Normativa Especies'!$M$2:$M$995,0)),"-") -> LESRPE | I14: =IFERROR(INDEX(FAUNA!$D$2:$D$134,MATCH(TRIM(A14),FAUNA!$E$1:E144,0)),"-") -> Sensibles a la alteración de su hábitat
A15: Alytes cisternasii | B15: Sapo partero ibérico | C15: Anfibios | D15: LESRPE | E15: — | F15: — | H15: =IFERROR(INDEX('Normativa Especies'!$H$2:$H$995,MATCH(TRIM(A15),'Normativa Especies'!$M$2:$M$995,0)),"-") -> LESRPE | I15: =IFERROR(INDEX(FAUNA!$D$2:$D$134,MATCH(TRIM(A15),FAUNA!$E$1:E145,0)),"-") -> -
... A132: Oenanthe hispanica | B132: Collalba rubia | C132: Aves | D132: LESRPE | E132: — | F132: — | H132: =IFERROR(INDEX('Normativa Especies'!$H$2:$H$995,MATCH(TRIM(A132),'Normativa Especies'!$M$2:$M$995,0)),"-") -> LESRPE | I132: =IFERROR(INDEX(FAUNA!$D$2:$D$134,MATCH(TRIM(A132),FAUNA!$E$1:E262,0)),"-") -> -
A134: TOTALES POR CATEGORÍA
A135: Categoría | B135: LESRPE/CEEA | C135: Cat. Madrid
A136: 🟠 En peligro de extinción | B136: 1 | C136: 0
A137: 🟡 Vulnerable | B137: 2 | C137: 4
A138: 🟢 Otro | B138: 64 | C138: 12
A140: Nota: 'LESRPE/CEEA' y 'Cat. Madrid' cuentan especies por fuente normativa de forma independiente; una misma especie puede figurar en ambas columnas si tiene protección tanto nacional como autonómica.

Sheet 🌿 Inventario Flora
A1: Inventario Florístico — Planta solar El Álamo
A2: CATEGORÍAS: | B2: 🟠 En peligro de extinción | C2: 🟡 Vulnerable | D2: 🟢 Otro
A3: Nombre científico | B3: Nombre común | C3: Grupo | D3: LESRPE/CEEA | E3: Cat. Madrid | F3: Normativa autonómica | H3: Cat. España | I3: Cat. amenaza (Listado/Catálogo Madrid)
A4: Anagallis tenella | B4: — | C4: Flora | D4: — | E4: — | F4: — | H4: =IFERROR(INDEX('Normativa Especies'!$H$2:$H$995,MATCH(TRIM(A4),'Normativa Especies'!$C$2:$C$995,0)),"-") -> - | I4: =IFERROR(INDEX(FLORA!$C$2:$C$107,MATCH(TRIM(A4),FLORA!$D$1:$D$107,0)),"-") -> -
A5: Anchusa undulata | B5: — | C5: Flora | D5: — | E5: — | F5: — | H5: =IFERROR(INDEX('Normativa Especies'!$H$2:$H$995,MATCH(TRIM(A5),'Normativa Especies'!$C$2:$C$995,0)),"-") -> - | I5: =IFERROR(INDEX(FLORA!$C$2:$C$107,MATCH(TRIM(A5),FLORA!$D$1:$D$107,0)),"-") -> -
A6: Apium inundatum | B6: — | C6: Flora | D6: — | E6: — | F6: — | H6: =IFERROR(INDEX('Normativa Especies'!$H$2:$H$995,MATCH(TRIM(A6),'Normativa Especies'!$C$2:$C$995,0)),"-") -> - | I6: =IFERROR(INDEX(FLORA!$C$2:$C$107,MATCH(TRIM(A6),FLORA!$D$1:$D$107,0)),"-") -> -
A7: Bromus hordeaceus | B7: — | C7: Flora | D7: — | E7: — | F7: — | H7: =IFERROR(INDEX('Normativa Especies'!$H$2:$H$995,MATCH(TRIM(A7),'Normativa Especies'!$C$2:$C$995,0)),"-") -> - | I7: =IFERROR(INDEX(FLORA!$C$2:$C$107,MATCH(TRIM(A7),FLORA!$D$1:$D$107,0)),"-") -> -
A8: Bromus rubens | B8: — | C8: Flora | D8: — | E8: — | F8: — | H8: =IFERROR(INDEX('Normativa Especies'!$H$2:$H$995,MATCH(TRIM(A8),'Normativa Especies'!$C$2:$C$995,0)),"-") -> - | I8: =IFERROR(INDEX(FLORA!$C$2:$C$107,MATCH(TRIM(A8),FLORA!$D$1:$D$107,0)),"-") -> -
A9: Bromus tectorum | B9: — | C9: Flora | D9: — | E9: — | F9: — | H9: =IFERROR(INDEX('Normativa Especies'!$H$2:$H$995,MATCH(TRIM(A9),'Normativa Especies'!$C$2:$C$995,0)),"-") -> - | I9: =IFERROR(INDEX(FLORA!$C$2:$C$107,MATCH(TRIM(A9),FLORA!$D$1:$D$107,0)),"-") -> -
A10: Coincya monensis subsp. orophila | B10: — | C10: Flora | D10: — | E10: — | F10: — | H10: =IFERROR(INDEX('Normativa Especies'!$H$2:$H$995,MATCH(TRIM(A10),'Normativa Especies'!$C$2:$C$995,0)),"-") -> - | I10: =IFERROR(INDEX(FLORA!$C$2:$C$107,MATCH(TRIM(A10),FLORA!$D$1:$D$107,0)),"-") -> -
A11: Euphorbia matritensis | B11: — | C11: Flora | D11: — | E11: — | F11: — | H11: =IFERROR(INDEX('Normativa Especies'!$H$2:$H$995,MATCH(TRIM(A11),'Normativa Especies'!$C$2:$C$995,0)),"-") -> - | I11: =IFERROR(INDEX(FLORA!$C$2:$C$107,MATCH(TRIM(A11),FLORA!$D$1:$D$107,0)),"-") -> -
A12: Gnaphalium uliginosum | B12: — | C12: Flora | D12: — | E12: — | F12: — | H12: =IFERROR(INDEX('Normativa Especies'!$H$2:$H$995,MATCH(TRIM(A12),'Normativa Especies'!$C$2:$C$995,0)),"-") -> - | I12: =IFERROR(INDEX(FLORA!$C$2:$C$107,MATCH(TRIM(A12),FLORA!$D$1:$D$107,0)),"-") -> -
A13: Hypericum australe | B13: — | C13: Flora | D13: — | E13: — | F13: — | H13: =IFERROR(INDEX('Normativa Especies'!$H$2:$H$995,MATCH(TRIM(A13),'Normativa Especies'!$C$2:$C$995,0)),"-") -> - | I13: =IFERROR(INDEX(FLORA!$C$2:$C$107,MATCH(TRIM(A13),FLORA!$D$1:$D$107,0)),"-") -> -
A14: Isolepis pseudosetacea | B14: — | C14: Flora | D14: — | E14: — | F14: — | H14: =IFERROR(INDEX('Normativa Especies'!$H$2:$H$995,MATCH(TRIM(A14),'Normativa Especies'!$C$2:$C$995,0)),"-") -> - | I14: =IFERROR(INDEX(FLORA!$C$2:$C$107,MATCH(TRIM(A14),FLORA!$D$1:$D$107,0)),"-") -> -
A15: Juncus articulatus | B15: — | C15: Flora | D15: — | E15: — | F15: — | H15: =IFERROR(INDEX('Normativa Especies'!$H$2:$H$995,MATCH(TRIM(A15),'Normativa Especies'!$C$2:$C$995,0)),"-") -> - | I15: =IFERROR(INDEX(FLORA!$C$2:$C$107,MATCH(TRIM(A15),FLORA!$D$1:$D$107,0)),"-") -> -
... A31: Veronica anagallis-aquatica subsp. anagallis-aquatica | B31: — | C31: Flora | D31: — | E31: — | F31: — | H31: =IFERROR(INDEX('Normativa Especies'!$H$2:$H$995,MATCH(TRIM(A31),'Normativa Especies'!$C$2:$C$995,0)),"-") -> - | I31: =IFERROR(INDEX(FLORA!$C$2:$C$107,MATCH(TRIM(A31),FLORA!$D$1:$D$107,0)),"-") -> -
A33: TOTALES POR CATEGORÍA
A34: Categoría | B34: LESRPE/CEEA | C34: Cat. Madrid
A36: Nota: 'LESRPE/CEEA' y 'Cat. Madrid' cuentan especies por fuente normativa de forma independiente; una misma especie puede figurar en ambas columnas si tiene protección tanto nacional como autonómica.

Sheet FAUNA
A1: Orden / Grupo | B1: Nombre común | C1: Nombre científico | D1: Categoria de amenaza | E1: Nombre científico
A2: Orthoptera | C2: Saga pedo (Tettigonidae) Palles | D2: En peligro de extinción | E2: Saga pedo
A3: Orthoptera | C3: Podisma carpetana (Catantopidae) Bolivar | D3: En peligro de extinción | E3: Podisma carpetana
A4: Lepidoptera | C4: Parnassius apollo (Papilionidae) Linnaeus | D4: En peligro de extinción | E4: Parnassius apollo
A5: Dyctyoptera | C5: Apteromantis aptera De la Fuente | D5: En peligro de extinción | E5: Apteromantis aptera
A6: Ephemeroptera | C6: Serratella hispanica (Ephemerelledae) Eaton | D6: Sensibles a la alteración de su hábitat | E6: Serratella hispanica
A7: Ephemeroptera | C7: Drunella paradinasi (Ephemerellidae) Tánago y Jalón | D7: Sensibles a la alteración de su hábitat | E7: Drunella paradinasi
A8: Odonata | C8: Cocnagrion mercuriale (Caenogriidae) Charpentier | D8: Sensibles a la alteración de su hábitat | E8: Cocnagrion mercuriale
A9: Orthoptera | C9: Steropleurus obsoletus (Tettigonidae) Bolivar | D9: Sensibles a la alteración de su hábitat | E9: Steropleurus obsoletus
A10: Orthoptera | C10: Dociostaurus crassiusculus (Acrididae) Pantel | D10: Sensibles a la alteración de su hábitat | E10: Dociostaurus crassiusculus
A11: Orthoptera | C11: Dociostaurus hispanicos (Acrididae) Bolivar | D11: Sensibles a la alteración de su hábitat | E11: Dociostaurus hispanicos
A12: Orthoptera | C12: Arcyptera tornosi (Acrididae) Bolivar | D12: Sensibles a la alteración de su hábitat | E12: Arcyptera tornosi
A13: Orthoptera | C13: Sciobia lusitanica (Gryllidae) Rambur | D13: Sensibles a la alteración de su hábitat | E13: Sciobia lusitanica
... A43: Lepidoptera | C43: Ocnogyna zoraida (Arctiidae) Graslin | D43: De interés especial | E43: Ocnogyna zoraida
A44: Peces | B44: Calandino | C44: Tropidophoxinellus alburnoides Steindachner | D44: En peligro de extinción | E44: Tropidophoxinellus alburnoides
A45: Peces | B45: Anguila | C45: Anguilla anguilla Linnaeus | D45: En peligro de extinción | E45: Anguilla anguilla
A46: Peces | B46: Colmilleja o Lamprehuela | C46: Cobitis calderoni Steindachner | D46: En peligro de extinción | E46: Cobitis calderoni
A47: Peces | B47: Barbo comiza | C47: Barbus comiza Bacescu | D47: En peligro de extinción | E47: Barbus comiza
A48: Anfibios | B48: Tritón alpino | C48: Triturus alpestris Wolterstorff | D48: En peligro de extinción | E48: Triturus alpestris
A49: Reptiles | B49: Galápago europeo | C49: Emys orbicularis Linnaeus | D49: En peligro de extinción | E49: Emys orbicularis
A50: Aves | B50: Alimoche | C50: Neophron percnopterus Linnaeus | D50: En peligro de extinción | E50: Neophron percnopterus
A51: Aves | B51: Águila Perdicera | C51: Hieraaetus fasciatus Vieillot | D51: En peligro de extinción | E51: Hieraaetus fasciatus
A52: Aves | B52: Águila Imperial ibérica | C52: Aquila adalberti C.L. Brehm | D52: En peligro de extinción | E52: Aquila adalberti
A53: Aves | B53: Cigüeña negra | C53: Ciconia nigra Linnaeus | D53: En peligro de extinción | E53: Ciconia nigra
A54: Aves | B54: Buitre negro | C54: Aegypius monachus Linnaeus | D54: En peligro de extinción | E54: Aegypius monachus
A55: Aves | B55: Cernícalo primilla | C55: Falco naumanni Fleischer | D55: En peligro de extinción | E55: Falco naumanni
... A134: Reptiles | B134: Lagarto verdinegro | C134: Lacerta schreiberi Bedriaga | D134: De interés especial | E134: Lacerta schreiberi

Sheet FLORA
A1: Nombre común | B1: Nombre científico | C1: Categoria de amenaza | D1: Nombre científico
B2: Hohenackeria polyodon Cosson et Durieu | C2: En peligro de extinción | D2: Hohenackeria polyodon
B3: Lycopodiella inundata C. Börner | C3: En peligro de extinción | D3: Lycopodiella inundata
B4: Narcissus pseudonarcissus confusus Linnaeus | C4: En peligro de extinción | D4: Narcissus pseudonarcissus confusus
B5: Polystichum lonchitis Roth | C5: En peligro de extinción | D5: Polystichum lonchitis
A6: Sapina | B6: Arthrocnemum machrostachyum (Delile) Ung.-Stern | C6: Sensibles a la alteración de su hábitat | D6: Arthrocnemum machrostachyum
A7: Jaguarzo amarillo | B7: Halimium commutatum Pau | C7: Sensibles a la alteración de su hábitat | D7: Halimium commutatum
A8: Toronjil silvestre | B8: Melittis melissophyllum Linnaeus | C8: Sensibles a la alteración de su hábitat | D8: Melittis melissophyllum
A9: Nébeda del Beltrán | B9: Nepeta beltranii Pau | C9: Sensibles a la alteración de su hábitat | D9: Nepeta beltranii
A10: Peralillo, piruétano | B10: Pyrus bourgaeana Decne | C10: Sensibles a la alteración de su hábitat | D10: Pyrus bourgaeana
A11: Jaramugo de Cavanilles | B11: Sisymbrium cavanillesianum Castrov. et Val. Berm. | C11: Sensibles a la alteración de su hábitat | D11: Sisymbrium cavanillesianum
A12: Acebo | B12: Ilex aquifolium Linnaeus | C12: Sensibles a la alteración de su hábitat | D12: Ilex aquifolium
A13: Sabina albar | B13: Juniperus thurifera Linnaeus | C13: Sensibles a la alteración de su hábitat | D13: Juniperus thurifera
A14: Tejo | B14: Taxus baccata Linnaeus | C14: Sensibles a la alteración de su hábitat | D14: Taxus baccata
A15: Olmo de montaña | B15: Ulmus glabra Hudson | C15: Sensibles a la alteración de su hábitat | D15: Ulmus glabra
A16: Fresno común | B16: Fraxinus excelsior Linnaeus | C16: Sensibles a la alteración de su hábitat | D16: Fraxinus excelsior
A17: Azucena silvestre | B17: Lilium martagon Linnaeus | C17: Sensibles a la alteración de su hábitat | D17: Lilium martagon
... A19: Serbal | B19: Sorbus torminalis (Linnaeus) Crantz. | C19: Sensibles a la alteración de su hábitat | D19: Sorbus torminalis
B20: Nitella flexilis (Linnaeus) Agardh. | C20: Sensibles a la alteración de su hábitat | D20: Nitella flexilis
B21: Nitella mucronata (A. Braun) Miquel | C21: Sensibles a la alteración de su hábitat | D21: Nitella mucronata
B22: Nitella translucens (Pers.) Agardh. | C22: Sensibles a la alteración de su hábitat | D22: Nitella translucens
B23: Riccia fluitans L. Emend. Lorbeer | C23: Sensibles a la alteración de su hábitat | D23: Riccia fluitans
B24: Isoetes histrix Bory | C24: Sensibles a la alteración de su hábitat | D24: Isoetes histrix
B25: Potamogeton perfoliatus Linnaeus | C25: Sensibles a la alteración de su hábitat | D25: Potamogeton perfoliatus
B26: Utricularia minor Linnaeus | C26: Sensibles a la alteración de su hábitat | D26: Utricularia minor
B27: Carex furva Webb | C27: Sensibles a la alteración de su hábitat | D27: Carex furva
B28: Carex umbrosa huetiana Host | C28: Sensibles a la alteración de su hábitat | D28: Carex umbrosa huetiana
B29: Clypeola eriocarpa Cav. | C29: Sensibles a la alteración de su hábitat | D29: Clypeola eriocarpa
B30: Eriophorum latifolium Hoppe | C30: Sensibles a la alteración de su hábitat | D30: Eriophorum latifolium
B31: Hyacinthoides non-scripta (L.) Chov. et Rothm. | C31: Sensibles a la alteración de su hábitat | D31: Hyacinthoides non-scripta
... B33: Juncus alpinoarticulatus auct non Chaix. | C33: Sensibles a la alteración de su hábitat | D33: Juncus alpinoarticulatus
A34: Guillomo | B34: Amelanchier ovalis Medicus | C34: Vulnerables | D34: Amelanchier ovalis
A35: Geranio de El Paular | B35: Erodium paularense Fdez. Gzlez. et Izco | C35: Vulnerables | D35: Erodium paularense
B36: Azolla caroliniana Willd | C36: Vulnerables | D36: Azolla caroliniana
B37: Callitriche truncata truncata Guss | C37: Vulnerables | D37: Callitriche truncata truncata
B38: Juncus bulbosus Linnaeus | C38: Vulnerables | D38: Juncus bulbosus
B39: Litorella uniflora (L.) Ascherson | C39: Vulnerables | D39: Litorella uniflora
B40: Ludwigia palustris (L.) Elliot | C40: Vulnerables | D40: Ludwigia palustris
B41: Menyanthes trifoliata Linnaeus | C41: Vulnerables | D41: Menyanthes trifoliata
B42: Potamogeton gramineus Linnaeus | C42: Vulnerables | D42: Potamogeton gramineus
B43: Potamogeton polygonifolius Pourret | C43: Vulnerables | D43: Potamogeton polygonifolius
A44: Aconito | B44: Aconitum napellus Linnaeus | C44: Vulnerables | D44: Aconitum napellus
A45: Carpazo | B45: Cistus psilosepalus Sweet | C45: Vulnerables | D45: Cistus psilosepalus
B46: Echium flavum Desf. | C46: Vulnerables | D46: Echium flavum
A47: Laurel de San Antonio | B47: Epilobium angustifolium Linnaeus | C47: Vulnerables | D47: Epilobium angustifolium
B48: Euphorbia broteri Daveau | C48: Vulnerables | D48: Euphorbia broteri
B49: Geum rivale Linnaeus | C49: Vulnerables | D49: Geum rivale
B50: Hypericum androsaemum Linnaeus | C50: Vulnerables | D50: Hypericum androsaemum
B51: Narcissus cantabricus DC | C51: Vulnerables | D51: Narcissus cantabricus
A52: Cerezo-aliso | B52: Prunus padus Linnaeus | C52: Vulnerables | D52: Prunus padus
B53: Ranunculus abnormis Cutanda et Willk | C53: Vulnerables | D53: Ranunculus abnormis
B54: Ranunculus nigrescens Freyn | C54: Vulnerables | D54: Ranunculus nigrescens
B55: Secale montanum Guss | C55: Vulnerables | D55: Secale montanum
B56: Luzula caespitosa Gay | C56: Vulnerables | D56: Luzula caespitosa
B57: Luzula sylvatica (Hudson) Gaudin | C57: Vulnerables | D57: Luzula sylvatica
B58: Neottia nidus-avis (L.) L.C.M. Rich | C58: Vulnerables | D58: Neottia nidus-avis
B59: Paris quadrifolia Linnaeus | C59: Vulnerables | D59: Paris quadrifolia
B60: Pedicularis comosa schizocalyx (Lange) Lainz | C60: Vulnerables | D60: Pedicularis comosa schizocalyx
B61: Phyteuma spicatum Linnaeus | C61: Vulnerables | D61: Phyteuma spicatum
B62: Pinguicula grandiflora Lam. | C62: Vulnerables | D62: Pinguicula grandiflora
B63: Platanthera bifolia (L.) L.C.M. Richard | C63: Vulnerables | D63: Platanthera bifolia
B64: Pyrola rotundifolia Linnaeus | C64: Vulnerables | D64: Pyrola rotundifolia
... B70: Utricularia australis R. Br. | C70: Vulnerables | D70: Utricularia australis
A71: Abedul | B71: Betula alba Linnaeus | C71: De interés especial | D71: Betula alba
A72: Avellano | B72: Corylus avellana Linnaeus | C72: De interés especial | D72: Corylus avellana
A73: Genciana | B73: Gentiana lutea Linnaeus | C73: De interés especial | D73: Gentiana lutea
A74: Manzano silvestre | B74: Malus sylvestris Miller | C74: De interés especial | D74: Malus sylvestris
A75: Rosa vellosa | B75: Rosa villosa Linnaeus | C75: De interés especial | D75: Rosa villosa
A76: Tamujo | B76: Securinega tinctoria (L.) Rothm. | C76: De interés especial | D76: Securinega tinctoria
A77: Arándano | B77: Vaccinium myrtillus Linnaeus | C77: De interés especial | D77: Vaccinium myrtillus
A78: Pítano | B78: Vella pseudocytisus Linnaeus | C78: De interés especial | D78: Vella pseudocytisus
A79: Roble albar | B79: Quercus petraea (Mattuschka) Liebl. | C79: De interés especial | D79: Quercus petraea
A80: Roble común | B80: Quercus robur (L.) Crantz | C80: De interés especial | D80: Quercus robur
A81: Mostajo | B81: Sorbus aria Linnaeus | C81: De interés especial | D81: Sorbus aria
A82: Serbal de cazadores | B82: Sorbus aucuparia Linnaeus | C82: De interés especial | D82: Sorbus aucuparia
... A87: Alcornoque | B87: Quercus suber Linnaeus | C87: De interés especial | D87: Quercus suber
B88: Callitriche lusitanica (F.X. Hartman) O. Schwarz | C88: De interés especial | D88: Callitriche lusitanica
B89: Eleocharis quinqueflora Linnaeus | C89: De interés especial | D89: Eleocharis quinqueflora
B90: Najas marina Linnaeus | C90: De interés especial | D90: Najas marina
B91: Ruppia maritima maritima Linnaeus | C91: De interés especial | D91: Ruppia maritima maritima
A92: Regaliz | B92: Glycyrrhiza glabra Linnaeus | C92: De interés especial | D92: Glycyrrhiza glabra
B93: Senecio boissieri D.C. | C93: De interés especial | D93: Senecio boissieri
A94: Eléboro blanco | B94: Veratrum album Linnaeus | C94: De interés especial | D94: Veratrum album
A95: Bola de nieve | B95: Viburnum opulus Linnaeus | C95: De interés especial | D95: Viburnum opulus
A96: Abedul común | B96: Betula pendula Roth. | C96: De interés especial | D96: Betula pendula

Sheet Normativa Especies
A1: Grupo Taxonómico | B1: TaxonID | C1: Nombre científico LESRPE / CEEA | D1: Nombre científico actualizado | E1: Rango taxonómico | F1: Nombre común | G1: Población referida | H1: Listado de Especies Silvestres en Régimen de Protección Especial (LESRPE)/ Categorías en el Catálogo Español de Especies Amenazadas (CEEA) | I1: Norma | J1: Situación anterior LESRPE / CEEA (en Normativa) | K1: Observaciones
A2: Anfibios | B2: 10909 | C2: Alytes cisternasii | D2: Alytes cisternasii Boscá, 1879 | E2: especie | F2: Sapo partero ibérico | H2: LESRPE | I2: Real Decreto 139/2011 | M2: =TRIM(C2) -> Alytes cisternasii
A3: Anfibios | B3: 11158 | C3: Alytes dickhilleni | D3: Alytes dickhilleni Arntzen & García-París, 1995 | E3: especie | F3: Sapo partero bético | H3: Vulnerable | I3: Real Decreto 139/2011 | M3: =TRIM(C3) -> Alytes dickhilleni
A4: Anfibios | B4: 11790 | C4: Alytes muletensis | D4: Alytes muletensis (Sanchiz & Adrover, 1977) | E4: especie | F4: Ferreret | H4: En peligro de extinción | I4: Real Decreto 139/2011 | M4: =TRIM(C4) -> Alytes muletensis
A5: Anfibios | B5: 11878 | C5: Alytes obstetricans | D5: Alytes obstetricans (Laurenti, 1768) | E5: especie | F5: Sapo partero común | H5: LESRPE | I5: Real Decreto 139/2011 | M5: =TRIM(C5) -> Alytes obstetricans
A6: Anfibios | B6: 16220 | C6: Bufo balearicus (= Bufo viridis) | D6: Bufotes viridis balearicus (Boettger, 1880) | E6: especie | F6: Sapo verde balear | H6: LESRPE | I6: Real Decreto 139/2011 | M6: =TRIM(C6) -> Bufo balearicus (= Bufo viridis)
A7: Anfibios | B7: 10762 | C7: Calotriton arnoldi | D7: Calotriton arnoldi Carranza & Amat, 2005 | E7: especie | F7: Tritón del Montseny | H7: En peligro de extinción | I7: Real Decreto 139/2011 | M7: =TRIM(C7) -> Calotriton arnoldi
A8: Anfibios | B8: 10769 | C8: Calotriton (Euproctus) asper | D8: Calotriton asper (Dugès, 1852) | E8: especie | F8: Tritón pirenaico | H8: LESRPE | I8: Real Decreto 139/2011 | M8: =TRIM(C8) -> Calotriton (Euproctus) asper
A9: Anfibios | B9: 11632 | C9: Chioglossa lusitanica | D9: Chioglossa lusitanica Bocage, 1864 | E9: especie | F9: Salamandra rabilarga | H9: Vulnerable | I9: Real Decreto 139/2011 | M9: =TRIM(C9) -> Chioglossa lusitanica
A10: Anfibios | B10: 11332 | C10: Discoglossus galganoi | D10: Discoglossus galganoi Capula, Nascetti, Lanza, Crespo & Bullini 1985 | E10: especie | F10: Sapillo pintojo ibérico | H10: LESRPE | I10: Real Decreto 139/2011 | M10: =TRIM(C10) -> Discoglossus galganoi
A11: Anfibios | B11: 24211 | C11: Discoglossus jeanneae | D11: Discoglossus galganoi jeanneae Busack, 1986 | E11: subespecie | F11: Sapillo pintojo meridional | H11: LESRPE | I11: Real Decreto 139/2011 | M11: =TRIM(C11) -> Discoglossus jeanneae
A12: Anfibios | B12: 11985 | C12: Discoglossus pictus | D12: Discoglossus pictus (Otth, 1837) | E12: especie | F12: Sapillo pintojo mediterráneo | H12: LESRPE | I12: Real Decreto 139/2011 | M12: =TRIM(C12) -> Discoglossus pictus
A13: Anfibios | B13: 24327 | C13: Bufo calamita | D13: Epidalea calamita (Laurenti, 1768) | E13: especie | F13: Sapo corredor | H13: LESRPE | I13: Real Decreto 139/2011 | M13: =TRIM(C13) -> Bufo calamita
A14: Anfibios | B14: 11717 | C14: Hyla meridionalis | D14: Hyla meridionalis Boettger, 1874 | E14: especie | F14: Ranita meridional | G14: Península y Baleares | H14: LESRPE | I14: Real Decreto 139/2011 | M14: =TRIM(C14) -> Hyla meridionalis
A15: Anfibios | B15: 16222 | C15: Hyla arborea | D15: Hyla molleri (Bedriaga, 1889) | E15: especie | F15: Ranita de San Antón | H15: LESRPE | I15: Real Decreto 139/2011 | M15: =TRIM(C15) -> Hyla arborea
A16: Anfibios | B16: 10729 | C16: Lissotriton boscai (antes Triturus boscai) | D16: Lissotriton boscai (Lataste, 1879) | E16: especie | F16: Tritón ibérico | H16: LESRPE | I16: Real Decreto 139/2011 | M16: =TRIM(C16) -> Lissotriton boscai (antes Triturus boscai)
A17: Anfibios | B17: 11431 | C17: Lissotriton helveticus (antes Triturus helveticus) | D17: Lissotriton helveticus (Razoumowsky, 1789) | E17: especie | F17: Tritón palmeado | H17: LESRPE | I17: Real Decreto 139/2011 | M17: =TRIM(C17) -> Lissotriton helveticus (antes Triturus helveticus)
A18: Anfibios | B18: 33080 | C18: Mesotriton alpestris (antes Triturus alpestris) | D18: Ichthyosaura alpestris (Laurenti, 1768) | E18: especie | F18: Tritón alpino | H18: Vulnerable | I18: Real Decreto 139/2011 | M18: =TRIM(C18) -> Mesotriton alpestris (antes Triturus alpestris)
A19: Anfibios | B19: 11108 | C19: Pelobates cultripes | D19: Pelobates cultripes (Cuvier, 1829) | E19: especie | F19: Sapo de espuelas | H19: LESRPE | I19: Real Decreto 139/2011 | M19: =TRIM(C19) -> Pelobates cultripes
A20: Anfibios | B20: 11490 | C20: Pelodytes ibericus (antes P. punctatus) | D20: Pelodytes ibericus Sánchez-Herráiz, Barbadillo, Machordom & Sanchiz, 2000 | E20: especie | F20: Sapillo moteado ibérico | H20: LESRPE | I20: Real Decreto 139/2011 | M20: =TRIM(C20) -> Pelodytes ibericus (antes P. punctatus)
A21: Anfibios | B21: 12037 | C21: Pelodytes punctatus | D21: Pelodytes punctatus (Daudin, 1802) | E21: especie | F21: Sapillo moteado común | H21: LESRPE | I21: Real Decreto 139/2011 | M21: =TRIM(C21) -> Pelodytes punctatus
A22: Anfibios | B22: 12420 | C22: Pleurodeles waltl | D22: Pleurodeles waltl Michahelles, 1830 | E22: especie | F22: Gallipato | H22: LESRPE | I22: Real Decreto 139/2011 | M22: =TRIM(C22) -> Pleurodeles waltl
A23: Anfibios | B23: 11128 | C23: Rana dalmatina | D23: Rana dalmatina Bonaparte, 1840 | E23: especie | F23: Rana ágil | H23: Vulnerable | I23: Real Decreto 139/2011 | M23: =TRIM(C23) -> Rana dalmatina
A24: Anfibios | B24: 11485 | C24: Rana iberica | D24: Rana iberica Boulenger, 1879 | E24: especie | F24: Rana patilarga | H24: LESRPE | I24: Real Decreto 139/2011 | M24: =TRIM(C24) -> Rana iberica
A25: Anfibios | B25: 12056 | C25: Rana pyrenaica | D25: Rana pyrenaica Serra-Cobo, 1993 | E25: especie | F25: Rana pirenaica | H25: Vulnerable | I25: Real Decreto 139/2011 | M25: =TRIM(C25) -> Rana pyrenaica
A26: Anfibios | B26: 12298 | C26: Rana temporaria | D26: Rana temporaria Linnaeus, 1758 | E26: especie | F26: Rana bermeja | H26: LESRPE | I26: Real Decreto 139/2011 | M26: =TRIM(C26) -> Rana temporaria
... A73: Aves | B73: 14010 | C73: Bulweria bulwerii | D73: Bulweria bulwerii (Jardine & Selby, 1828) | E73: especie | F73: Petrel de Bulwer | H73: LESRPE | I73: Real Decreto 139/2011 | M73: =TRIM(C73) -> Bulweria bulwerii
A74: Aves | B74: 11889 | C74: Burhinus oedicnemus distinctus | D74: Burhinus oedicnemus distinctus (Bannerman, 1914) | E74: subespecie | F74: Alcaraván común canario | G74: Canarias Centrales y Occidentales | H74: Vulnerable | I74: Real Decreto 139/2011 | M74: =TRIM(C74) -> Burhinus oedicnemus distinctus
A75: Aves | B75: 11888 | C75: Burhinus oedicnemus oedicnemus/insularum | D75: Burhinus oedicnemus insularum (Sassi, 1908) | E75: subespecie | F75: Alcaraván majorero | G75: Canarias Orientales | H75: LESRPE | I75: Real Decreto 139/2011 | K75: Nombre científico actualizado: Burhinus oedicnemus insularum (Sassi, 1908) Nombre común actualizado: Alcaraván majorero Población referida actualizada: Canarias Orientales | M75: =TRIM(C75) -> Burhinus oedicnemus oedicnemus/insularum
A76: Aves | B76: 28443 | C76: Burhinus oedicnemus oedicnemus/insularum | D76: Burhinus oedicnemus oedicnemus (Linnaeus, 1758) | E76: subespecie | F76: Alcaraván común | G76: Península y Baleares | H76: LESRPE | I76: Real Decreto 139/2011 | K76: Nombre científico actualizado: Burhinus oedicnemus oedicnemus (Linnaeus, 1758) Nombre común actualizado: Alcaraván común Población referida actualizada: Península y Baleares | M76: =TRIM(C76) -> Burhinus oedicnemus oedicnemus/insularum
A77: Aves | B77: 10922 | C77: Buteo buteo | D77: Buteo buteo (Linnaeus, 1758) | E77: especie | F77: Ratonero común | H77: LESRPE | I77: Real Decreto 139/2011 | M77: =TRIM(C77) -> Buteo buteo
A78: Aves | B78: 10734 | C78: Calandrella brachydactyla | D78: Calandrella brachydactyla (Leisler, 1814) | E78: especie | F78: Terrera común | H78: LESRPE | I78: Real Decreto 139/2011 | M78: =TRIM(C78) -> Calandrella brachydactyla
A79: Aves | B79: 33007 | C79: Calandrella rufescens | D79: Alaudala rufescens (Vieillot, 1819) | E79: especie | F79: Terrera marismeña | H79: LESRPE | I79: Real Decreto 139/2011 | M79: =TRIM(C79) -> Calandrella rufescens
A80: Aves | B80: 10649 | C80: Calidris alba | D80: Calidris alba (Pallas, 1764) | E80: especie | F80: Correlimos tridáctilo | H80: LESRPE | I80: Real Decreto 139/2011 | M80: =TRIM(C80) -> Calidris alba
A81: Aves | B81: 10678 | C81: Calidris alpina | D81: Calidris alpina (Linnaeus, 1758) | E81: especie | F81: Correlimos común | H81: LESRPE | I81: Real Decreto 139/2011 | M81: =TRIM(C81) -> Calidris alpina
A82: Aves | B82: 10957 | C82: Calidris canutus | D82: Calidris canutus (Linnaeus, 1758) | E82: especie | F82: Correlimos gordo | H82: LESRPE | I82: Real Decreto 139/2011 | M82: =TRIM(C82) -> Calidris canutus
A83: Aves | B83: 11262 | C83: Calidris ferruginea | D83: Calidris ferruginea (Pontoppidan, 1763) | E83: especie | F83: Correlimos zarapitín | H83: LESRPE | I83: Real Decreto 139/2011 | M83: =TRIM(C83) -> Calidris ferruginea
A84: Aves | B84: 16339 | C84: Calidris maritima | D84: Calidris maritima (Brünnich, 1764) | E84: especie | F84: Correlimos oscuro | H84: LESRPE | I84: Real Decreto 139/2011 | M84: =TRIM(C84) -> Calidris maritima
A85: Aves | B85: 11745 | C85: Calidris minuta | D85: Calidris minuta (Leisler, 1812) | E85: especie | F85: Correlimos menudo | H85: LESRPE | I85: Real Decreto 139/2011 | M85: =TRIM(C85) -> Calidris minuta
A86: Aves | B86: 32348 | C86: Calonectris diomedea borealis | D86: Calonectris borealis (Cory, 1881) | E86: especie | F86: Pardela cenicienta atlántica | H86: LESRPE | I86: Orden TEC/596/2019 | J86: LESRPE como Calonectris diomedea borealis (Real Decreto 139/2011) | K86: En Real Decreto 139/2011 como Calonectris diomedea borealis: Nombre común anterior: Pardela cenicienta Población referida anterior: Atlántico | M86: =TRIM(C86) -> Calonectris diomedea borealis
A87: Aves | B87: 11166 | C87: Calonectris diomedea diomedea | D87: Calonectris diomedea diomedea Scopoli, 1769 | E87: especie | F87: Pardela cenicienta | H87: Vulnerable | I87: Real Decreto 139/2011 | K87: Nombre común actualizado: Pardela cenicienta mediterránea | M87: =TRIM(C87) -> Calonectris diomedea diomedea
A88: Aves | B88: 16333 | C88: Calidris temminckii | D88: Calidris temminckii (Leisler, 1812) | E88: especie | F88: Correlimos de Temminck | H88: LESRPE | I88: Real Decreto 139/2011 | M88: =TRIM(C88) -> Calidris temminckii
A89: Aves | B89: 11229 | C89: Caprimulgus europaeus | D89: Caprimulgus europaeus Linnaeus, 1758 | E89: especie | F89: Chotacabras europeo | H89: LESRPE | I89: Real Decreto 139/2011 | M89: =TRIM(C89) -> Caprimulgus europaeus
A90: Aves | B90: 12122 | C90: Caprimulgus ruficollis | D90: Caprimulgus ruficollis Temminck, 1820 | E90: especie | F90: Chotacabras pardo | H90: LESRPE | I90: Real Decreto 139/2011 | M90: =TRIM(C90) -> Caprimulgus ruficollis
A91: Aves | B91: 33009 | C91: Carduelis spinus | D91: Spinus spinus (Linnaeus, 1758) | E91: especie | F91: Lúgano | H91: LESRPE | I91: Real Decreto 139/2011 | M91: =TRIM(C91) -> Carduelis spinus
A92: Aves | B92: 11327 | C92: Cercotrichas galactotes | D92: Cercotrichas galactotes (Temminck, 1820) | E92: especie | F92: Alzacola | H92: Vulnerable | I92: Real Decreto 139/2011 | M92: =TRIM(C92) -> Cercotrichas galactotes
A93: Aves | B93: 10733 | C93: Certhia brachydactyla | D93: Certhia brachydactyla Brehm, CL, 1820 | E93: especie | F93: Agateador común | H93: LESRPE | I93: Real Decreto 139/2011 | M93: =TRIM(C93) -> Certhia brachydactyla
A94: Aves | B94: 11250 | C94: Certhia familiaris | D94: Certhia familiaris Linnaeus, 1758 | E94: especie | F94: Agateador norteño | H94: LESRPE | I94: Real Decreto 139/2011 | M94: =TRIM(C94) -> Certhia familiaris
A95: Aves | B95: 11003 | C95: Cettia cetti | D95: Cettia cetti (Temminck, 1820) | E95: especie | F95: Ruiseñor bastardo | H95: LESRPE | I95: Real Decreto 139/2011 | M95: =TRIM(C95) -> Cettia cetti
A96: Aves | B96: 10664 | C96: Charadrius alexandrinus | D96: Charadrius alexandrinus Linnaeus, 1758 | E96: especie | F96: Chorlitejo patinegro | G96: Península y Baleares | H96: LESRPE | I96: Real Decreto 139/2011 | M96: =TRIM(C96) -> Charadrius alexandrinus
A97: Aves | B97: 10664 | C97: Charadrius alexandrinus | D97: Charadrius alexandrinus Linnaeus, 1758 | E97: especie | F97: Chorlitejo patinegro | G97: Canarias | H97: Vulnerable | I97: Real Decreto 139/2011 | M97: =TRIM(C97) -> Charadrius alexandrinus
A98: Aves | B98: 11179 | C98: Charadrius dubius | D98: Charadrius dubius Scopoli, 1786 | E98: especie | F98: Chorlitejo chico | H98: LESRPE | I98: Real Decreto 139/2011 | M98: =TRIM(C98) -> Charadrius dubius
A99: Aves | B99: 11442 | C99: Charadrius hiaticula | D99: Charadrius hiaticula Linnaeus, 1758 | E99: especie | F99: Chorlitejo grande | H99: LESRPE | I99: Real Decreto 139/2011 | M99: =TRIM(C99) -> Charadrius hiaticula
A100: Aves | B100: 11787 | C100: Charadrius (Eudromias) morinellus | D100: Charadrius morinellus Linnaeus, 1758 | E100: especie | F100: Chorlito carambolo | H100: Vulnerable | I100: Real Decreto 139/2011 | M100: =TRIM(C100) -> Charadrius (Eudromias) morinellus
A101: Aves | B101: 11182 | C101: Chersophilus duponti | D101: Chersophilus duponti (Vieillot, 1824) | E101: especie | F101: Alondra de Dupont o ricotí | H101: En peligro de extinción | I101: Orden TED/339/2023 | J101: Vulnerable (Real Decreto 139/2011) | M101: =TRIM(C101) -> Chersophilus duponti
A102: Aves | B102: 12363 | C102: Chlamydotis undulata | D102: Chlamydotis undulata (Jacquin, 1784) | E102: especie | F102: Avutarda hubara | H102: En peligro de extinción | I102: Real Decreto 139/2011 | M102: =TRIM(C102) -> Chlamydotis undulata
A103: Aves | B103: 14085 | C103: Chlidonias hybridus | D103: Chlidonias hybrida (Pallas, 1811) | E103: especie | F103: Fumarel cariblanco | H103: LESRPE | I103: Real Decreto 139/2011 | M103: =TRIM(C103) -> Chlidonias hybridus
A104: Aves | B104: 14087 | C104: Chlidonias leucopterus | D104: Chlidonias leucopterus (Temminck, 1815) | E104: especie | F104: Fumarel aliblanco | H104: LESRPE | I104: Real Decreto 139/2011 | M104: =TRIM(C104) -> Chlidonias leucopterus
A105: Aves | B105: 14086 | C105: Chlidonias niger | D105: Chlidonias niger (Linnaeus, 1758) | E105: especie | F105: Fumarel común | H105: En peligro de extinción | I105: Real Decreto 139/2011 | M105: =TRIM(C105) -> Chlidonias niger
A106: Aves | B106: 11307 | C106: Corvus frugilegus Linnaeus, 1758 | D106: Corvus frugilegus Linnaeus, 1758 | E106: especie | F106: Graja | H106: LESRPE | I106: Orden TED/452/2025 | M106: =TRIM(C106) -> Corvus frugilegus Linnaeus, 1758
A107: Aves | B107: 16358 | C107: Larus genei | D107: Chroicocephalus genei (Brème, 1839) | E107: especie | F107: Gaviota picofina | H107: LESRPE | I107: Real Decreto 139/2011 | M107: =TRIM(C107) -> Larus genei
A108: Aves | B108: 10891 | C108: Ciconia ciconia | D108: Ciconia ciconia (Linnaeus, 1758) | E108: especie | F108: Cigüeña blanca | H108: LESRPE | I108: Real Decreto 139/2011 | M108: =TRIM(C108) -> Ciconia ciconia
A109: Aves | B109: 11841 | C109: Ciconia nigra | D109: Ciconia nigra (Linnaeus, 1758) | E109: especie | F109: Cigüeña negra | H109: Vulnerable | I109: Real Decreto 139/2011 | M109: =TRIM(C109) -> Ciconia nigra
A110: Aves | B110: 10894 | C110: Cinclus cinclus | D110: Cinclus cinclus (Linnaeus, 1758) | E110: especie | F110: Mirlo acuático | H110: LESRPE | I110: Real Decreto 139/2011 | M110: =TRIM(C110) -> Cinclus cinclus
A111: Aves | B111: 11336 | C111: Circaetus gallicus | D111: Circaetus gallicus (Gmelin, JF, 1788) | E111: especie | F111: Águila culebrera | H111: LESRPE | I111: Real Decreto 139/2011 | M111: =TRIM(C111) -> Circaetus gallicus
A112: Aves | B112: 11024 | C112: Circus aeruginosus | D112: Circus aeruginosus (Linnaeus, 1758) | E112: especie | F112: Aguilucho lagunero occidental | H112: LESRPE | I112: Real Decreto 139/2011 | M112: =TRIM(C112) -> Circus aeruginosus
A113: Aves | B113: 11120 | C113: Circus cyaneus | D113: Circus cyaneus (Linnaeus, 1766) | E113: especie | F113: Aguilucho pálido | H113: LESRPE | I113: Real Decreto 139/2011 | M113: =TRIM(C113) -> Circus cyaneus
... A122: Aves | B122: 10952 | C122: Cuculus canorus | D122: Cuculus canorus Linnaeus, 1758 | E122: especie | F122: Cuco | H122: LESRPE | I122: Real Decreto 139/2011 | M122: =TRIM(C122) -> Cuculus canorus
A123: Aves | B123: 11113 | C123: Cursorius cursor | D123: Cursorius cursor (Latham, 1787) | E123: especie | F123: Engaña | G123: Canarias | H123: Vulnerable | I123: Real Decreto 139/2011 | M123: =TRIM(C123) -> Cursorius cursor
A124: Aves | B124: 11113 | C124: Cursorius cursor | D124: Cursorius cursor (Latham, 1787) | E124: especie | F124: Corredor sahariano | G124: Península | H124: LESRPE | I124: Real Decreto 139/2011 | M124: =TRIM(C124) -> Cursorius cursor
A125: Aves | B125: 16423 | C125: Cyanistes caeruleus | D125: Cyanistes caeruleus (Linnaeus, 1758) | E125: especie | F125: Herrerillo común | H125: LESRPE | I125: Real Decreto 139/2011 | M125: =TRIM(C125) -> Cyanistes caeruleus
A126: Aves | B126: 80935 | C126: Cyanopica cyanus | D126: Cyanopica cooki Bonaparte, 1850 | E126: especie | F126: Rabilargo | H126: LESRPE | I126: Real Decreto 139/2011 | M126: =TRIM(C126) -> Cyanopica cyanus
A127: Aves | B127: 12368 | C127: Delichon urbicum | D127: Delichon urbicum (Linnaeus, 1758) | E127: especie | F127: Avión común | H127: LESRPE | I127: Real Decreto 139/2011 | M127: =TRIM(C127) -> Delichon urbicum
A128: Aves | B128: 11591 | C128: Dendrocopos leucotos | D128: Dendrocopos leucotos (Bechstein, 1802) | E128: especie | F128: Pico dorsiblanco | H128: En peligro de extinción | I128: Real Decreto 139/2011 | M128: =TRIM(C128) -> Dendrocopos leucotos
A129: Aves | B129: 11649 | C129: Dendrocopos major | D129: Dendrocopos major (Linnaeus, 1758) | E129: especie | F129: Pico picapinos | H129: LESRPE | I129: Real Decreto 139/2011 | M129: =TRIM(C129) -> Dendrocopos major
A130: Aves | B130: 79181 | C130: Dendrocopos medius | D130: Dendrocoptes medius (Linnaeus, 1758) | E130: especie | F130: Pico mediano | H130: LESRPE | I130: Real Decreto 139/2011 | M130: =TRIM(C130) -> Dendrocopos medius
A131: Aves | B131: 33015 | C131: Dendrocopos minor | D131: Dryobates minor (Linnaeus, 1758) | E131: especie | F131: Pico menor | H131: LESRPE | I131: Real Decreto 139/2011 | M131: =TRIM(C131) -> Dendrocopos minor
A132: Aves | B132: 11684 | C132: Dryocopus martius | D132: Dryocopus martius (Linnaeus, 1758) | E132: especie | F132: Pito negro | H132: LESRPE | I132: Real Decreto 139/2011 | M132: =TRIM(C132) -> Dryocopus martius
A133: Aves | B133: 23748 | C133: Egretta alba | D133: Ardea alba Linnaeus, 1758 | E133: especie | F133: Garceta grande | H133: LESRPE | I133: Real Decreto 139/2011 | M133: =TRIM(C133) -> Egretta alba
A134: Aves | B134: 11340 | C134: Egretta garzetta | D134: Egretta garzetta (Linnaeus, 1766) | E134: especie | F134: Garceta común | H134: LESRPE | I134: Real Decreto 139/2011 | M134: =TRIM(C134) -> Egretta garzetta
A135: Aves | B135: 10930 | C135: Elanus caeruleus | D135: Elanus caeruleus (Desfontaines, 1789) | E135: especie | F135: Elanio común | H135: LESRPE | I135: Real Decreto 139/2011 | M135: =TRIM(C135) -> Elanus caeruleus
A136: Aves | B136: 10890 | C136: Emberiza cia | D136: Emberiza cia Linnaeus, 1766 | E136: especie | F136: Escribano montesino | H136: LESRPE | I136: Real Decreto 139/2011 | M136: =TRIM(C136) -> Emberiza cia
... A139: Aves | B139: 11476 | C139: Emberiza hortulana | D139: Emberiza hortulana Linnaeus, 1758 | E139: especie | F139: Escribano hortelano | H139: LESRPE | I139: Real Decreto 139/2011 | M139: =TRIM(C139) -> Emberiza hortulana
A140: Aves | B140: 12162 | C140: Emberiza schoeniclus schoeniclus | D140: Emberiza schoeniclus schoeniclus (Linnaeus, 1758) | E140: subespecie | F140: Escribano palustre | H140: LESRPE | I140: Real Decreto 139/2011 | K140: Nombre común actualizado: Escribano palustre norteño | M140: =TRIM(C140) -> Emberiza schoeniclus schoeniclus
A141: Aves | B141: 12165 | C141: Emberiza schoeniclus whiterby/lusitanica | D141: Emberiza schoeniclus lusitanica Steinbacher, 1930 | E141: subespecie | F141: Escribano palustre norteño | H141: En peligro de extinción | I141: Real Decreto 139/2011 | K141: Nombre científico actualizado: Emberiza schoeniclus lusitanica Steinbacher, 1930 Nombre común actualizado: Escribano palustre iberooccidental | M141: =TRIM(C141) -> Emberiza schoeniclus whiterby/lusitanica
A142: Aves | B142: 12164 | C142: Emberiza schoeniclus whiterby/lusitanica | D142: Emberiza schoeniclus witherbyi von Jordans, 1923 | E142: subespecie | F142: Escribano palustre iberooccidental | H142: En peligro de extinción | I142: Real Decreto 139/2011 | K142: Nombre científico actualizado: Emberiza schoeniclus whiterby von Jordans, 1923 Nombre común actualizado: Escribano palustre iberooriental | M142: =TRIM(C142) -> Emberiza schoeniclus whiterby/lusitanica
A143: Aves | B143: 12111 | C143: Erithacus rubecula | D143: Erithacus rubecula (Linnaeus, 1758) | E143: especie | F143: Petirrojo | H143: LESRPE | I143: Real Decreto 139/2011 | M143: =TRIM(C143) -> Erithacus rubecula
A144: Aves | B144: 11059 | C144: Falco columbarius | D144: Falco columbarius Linnaeus, 1758 | E144: especie | F144: Esmerejón | H144: LESRPE | I144: Real Decreto 139/2011 | M144: =TRIM(C144) -> Falco columbarius
A145: Aves | B145: 11198 | C145: Falco eleonorae | D145: Falco eleonorae Géné, 1839 | E145: especie | F145: Halcón de Eleonora | H145: LESRPE | I145: Real Decreto 139/2011 | M145: =TRIM(C145) -> Falco eleonorae
A146: Aves | B146: 11817 | C146: Falco naumanni | D146: Falco naumanni Fleischer, JG, 1818 | E146: especie | F146: Cernícalo primilla | H146: LESRPE | I146: Real Decreto 139/2011 | M146: =TRIM(C146) -> Falco naumanni
A147: Aves | B147: 11963 | C147: Falco peregrinus | D147: Falco peregrinus Tunstall, 1771 | E147: especie | F147: Halcón peregrino | H147: LESRPE | I147: Real Decreto 139/2011 | M147: =TRIM(C147) -> Falco peregrinus
A148: Aves | B148: 32346 | C148: Falco pelegrinoides | D148: Falco peregrinus pelegrinoides Temminck, 1829 | E148: subespecie | F148: Halcón tagarote | H148: En peligro de extinción | I148: Orden TEC/596/2019 | J148: En peligro de extinción como Falco pelegrinoides (Real Decreto 139/2011) | M148: =TRIM(C148) -> Falco pelegrinoides
A149: Aves | B149: 12262 | C149: Falco subbuteo | D149: Falco subbuteo Linnaeus, 1758 | E149: especie | F149: Alcotán europeo | H149: LESRPE | I149: Real Decreto 139/2011 | M149: =TRIM(C149) -> Falco subbuteo
A150: Aves | B150: 12321 | C150: Falco tinnunculus | D150: Falco tinnunculus Linnaeus, 1758 | E150: especie | F150: Cernícalo común | H150: LESRPE | I150: Real Decreto 139/2011 | M150: =TRIM(C150) -> Falco tinnunculus
A151: Aves | B151: 16303 | C151: Falco vespertinus | D151: Falco vespertinus Linnaeus, 1766 | E151: especie | F151: Cernícalo patirrojo | H151: LESRPE | I151: Real Decreto 139/2011 | M151: =TRIM(C151) -> Falco vespertinus
A152: Aves | B152: 11483 | C152: Ficedula hypoleuca | D152: Ficedula hypoleuca (Pallas, 1764) | E152: especie | F152: Papamoscas cerrojillo | H152: LESRPE | I152: Real Decreto 139/2011 | M152: =TRIM(C152) -> Ficedula hypoleuca
A153: Aves | B153: 14092 | C153: Fratercula arctica | D153: Fratercula arctica (Linnaeus, 1758) | E153: especie | F153: Frailecillo atlántico | H153: LESRPE | I153: Real Decreto 139/2011 | M153: =TRIM(C153) -> Fratercula arctica
A154: Aves | B154: 11047 | C154: Fringilla coelebs | D154: Fringilla coelebs Linnaeus, 1758 | E154: especie | F154: Pinzón vulgar | G154: Canarias | H154: LESRPE | I154: Real Decreto 139/2011 | M154: =TRIM(C154) -> Fringilla coelebs
A155: Aves | B155: 16433 | C155: Fringilla montifringilla | D155: Fringilla montifringilla Linnaeus, 1758 | E155: especie | F155: Pinzón real | H155: LESRPE | I155: Real Decreto 139/2011 | M155: =TRIM(C155) -> Fringilla montifringilla
A156: Aves | B156: 33011 | C156: Fringilla teydea polatzeki | D156: Fringilla polatzeki Hartert, 1905 | E156: especie | F156: Pinzón azul de Gran Canaria | H156: En peligro de extinción | I156: Real Decreto 139/2011 | M156: =TRIM(C156) -> Fringilla teydea polatzeki
...
